enquire_country.py
prodigyhelmsman.py
prodigyhelmsmanwsgi.py
sqlalchemy_test.py
prodigyhelmsman/__init__.py
prodigyhelmsman/enquire_country.py
prodigyhelmsman/prodigyhelmsman.py
prodigyhelmsman/prodigyhelmsmanwsgi.py
tests/__init__.py
tests/conftest.py
tests/test_prodigyhelmsman.py
ProdigyHelmsman-0.0.4.dist-info/LICENSE
ProdigyHelmsman-0.0.4.dist-info/METADATA
ProdigyHelmsman-0.0.4.dist-info/WHEEL
ProdigyHelmsman-0.0.4.dist-info/entry_points.txt
ProdigyHelmsman-0.0.4.dist-info/namespace_packages.txt
ProdigyHelmsman-0.0.4.dist-info/top_level.txt
ProdigyHelmsman-0.0.4.dist-info/RECORD
